Metadata-Version: 2.1
Name: jarvis-assistant-bot
Version: 1.4
Summary: Jarvis is a personal assistant application that allows you to manage your address book with contacts. The application provides features to add, remove, change, save, and load contacts, making it easier to organize your personal or professional network. In addition, Jarvis integrates with ChatGPT, an AI language model, to provide interactive chat functionality. And to add some entertainment after a hard working day, Jarvis also includes a fun game about Bandera-goose.
Home-page: https://github.com/UkrainianEagleOwl/tp_personal_assistant/tree/97c820e0779d54e488d5d824cce404b06bb4e654
Author: Dmytro Filin, Illya Grygoriev, Dmytro Klymenko, Dmytro Paukov, Alexandr 
Project-URL: Homepage, https://github.com/UkrainianEagleOwl/tp_personal_assistant
Project-URL: Bug Tracker, https://github.com/UkrainianEagleOwl/tp_personal_assistant/issues
Classifier: Programming Language :: Python :: 3
Classifier: License :: OSI Approved :: MIT License
Classifier: Operating System :: OS Independent
Requires-Python: >=3.7
License-File: LICENSE
Requires-Dist: prettytable
Requires-Dist: prompt-toolkit
Requires-Dist: colorama
Requires-Dist: cryptography
Requires-Dist: openai
Requires-Dist: keyboard
Requires-Dist: pygame
